chuk_acp_agent/__init__.py
chuk_acp_agent/cli.py
chuk_acp_agent/exceptions.py
chuk_acp_agent/py.typed
chuk_acp_agent/agent/__init__.py
chuk_acp_agent/agent/base.py
chuk_acp_agent/agent/context.py
chuk_acp_agent/agent/interactive.py
chuk_acp_agent/agent/session.py
chuk_acp_agent/capabilities/__init__.py
chuk_acp_agent/capabilities/filesystem.py
chuk_acp_agent/capabilities/terminal.py
chuk_acp_agent/integrations/__init__.py
chuk_acp_agent/integrations/mcp_tools.py
chuk_acp_agent/middlewares/__init__.py
chuk_acp_agent/models/__init__.py
chuk_acp_agent/models/mcp.py
chuk_acp_agent/models/tool.py
chuk_acp_agent/models/tool_result.py
chuk_acp_agent-0.2.1.dist-info/METADATA
chuk_acp_agent-0.2.1.dist-info/WHEEL
chuk_acp_agent-0.2.1.dist-info/entry_points.txt
chuk_acp_agent-0.2.1.dist-info/licenses/LICENSE
chuk_acp_agent-0.2.1.dist-info/RECORD
