Metadata-Version: 2.4
Name: chuk-acp-agent
Version: 0.2.1
Summary: Opinionated agent kit for building sophisticated ACP agents
Project-URL: Homepage, https://github.com/chrishayuk/chuk-acp-agent
Project-URL: Repository, https://github.com/chrishayuk/chuk-acp-agent
Project-URL: Issues, https://github.com/chrishayuk/chuk-acp-agent/issues
Author-email: Chris Hay <chris@chrishay.com>
License: MIT
License-File: LICENSE
Keywords: acp,agent,editor,llm,mcp
Classifier: Development Status :: 3 - Alpha
Classifier: Intended Audience :: Developers
Classifier: License :: OSI Approved :: MIT License
Classifier: Programming Language :: Python :: 3
Classifier: Programming Language :: Python :: 3.11
Classifier: Programming Language :: Python :: 3.12
Requires-Python: >=3.11
Requires-Dist: anyio>=4.0.0
Requires-Dist: chuk-acp>=0.3.2
Requires-Dist: chuk-tool-processor>=0.9.7
Requires-Dist: pydantic>=2.0.0
Provides-Extra: all
Requires-Dist: mypy>=1.8.0; extra == 'all'
Requires-Dist: pytest-asyncio>=0.23.0; extra == 'all'
Requires-Dist: pytest-cov>=4.1.0; extra == 'all'
Requires-Dist: pytest>=8.0.0; extra == 'all'
Requires-Dist: ruff>=0.1.0; extra == 'all'
Provides-Extra: dev
Requires-Dist: mypy>=1.8.0; extra == 'dev'
Requires-Dist: pytest-asyncio>=0.23.0; extra == 'dev'
Requires-Dist: pytest-cov>=4.1.0; extra == 'dev'
Requires-Dist: pytest>=8.0.0; extra == 'dev'
Requires-Dist: ruff>=0.1.0; extra == 'dev'
